pygamp/__init__.py
pygamp/app.py
pygamp/custom_definitions.py
pygamp/ecommerce.py
pygamp/enhanced_ecommerce.py
pygamp/events.py
pygamp/exceptions.py
pygamp/pageviews.py
pygamp/social_interactions.py
pygamp/transport.py
pygamp-0.113.dist-info/LICENSE.txt
pygamp-0.113.dist-info/METADATA
pygamp-0.113.dist-info/WHEEL
pygamp-0.113.dist-info/top_level.txt
pygamp-0.113.dist-info/RECORD
