Metadata-Version: 2.1
Name: pygamp
Version: 0.113
Summary: pygamp is a Python package for Google Analytics Measurement Protocol
Home-page: https://github.com/flyandlure/pygamp
Author: Matt Clarke
Author-email: matt@flyandlure.org
License: MIT
Download-URL: https://github.com/flyandlure/pygamp/archive/master.zip
Keywords: python,google analytics,ga,measurement protocol,universal analytics
Platform: UNKNOWN
Classifier: Development Status :: 3 - Alpha
Classifier: Intended Audience :: Developers
Classifier: Topic :: Software Development :: Libraries :: Python Modules
Classifier: License :: OSI Approved :: MIT License
Classifier: Programming Language :: Python :: 3.6
License-File: LICENSE.txt
